{
  "game_class": "RPS",
  "sprite_folder": "rps",
  "default_sprite_set": "rps_base",
  "category": "strategy",
  "tier": "trash",

  "variants": [
  {
    "clone_index": 0,
    "name": "RPS Classic",
    "flavor_text": "Rock, Paper, Scissors - best of 5. Beat the AI!"
  },
  {
    "clone_index": 1,
    "name": "RPS Quick Match",
    "difficulty_modifier": 0.8,
    "rounds_to_win": 1,
    "flavor_text": "Sudden death! One round decides everything"
  },
  {
    "clone_index": 2,
    "name": "RPS Pattern Repeater",
    "difficulty_modifier": 0.9,
    "rounds_to_win": 5,
    "ai_pattern": "repeat_last",
    "flavor_text": "AI repeats its last throw. Exploit the pattern!"
  },
  {
    "clone_index": 3,
    "name": "RPS Counter Master",
    "difficulty_modifier": 1.3,
    "rounds_to_win": 5,
    "ai_pattern": "counter_player",
    "flavor_text": "AI counters YOUR last throw. Don't be predictable!"
  },
  {
    "clone_index": 4,
    "name": "RPS Marathon",
    "difficulty_modifier": 1.2,
    "rounds_to_win": 10,
    "flavor_text": "Best of 19 rounds. Endurance and strategy required"
  },
  {
    "clone_index": 5,
    "name": "Big Bang Theory",
    "difficulty_modifier": 1.3,
    "game_mode": "rpsls",
    "rounds_to_win": 5,
    "flavor_text": "Rock Paper Scissors Lizard Spock! R/P/S/L/V keys"
  },
  {
    "clone_index": 6,
    "name": "RPS Elemental",
    "difficulty_modifier": 1.3,
    "game_mode": "rpsfb",
    "rounds_to_win": 5,
    "flavor_text": "Rock Paper Scissors Fire Water! R/P/S/F/W keys"
  },
  {
    "clone_index": 7,
    "name": "RPS Cycle Master",
    "difficulty_modifier": 1.1,
    "ai_pattern": "pattern_cycle",
    "rounds_to_win": 5,
    "flavor_text": "AI cycles through options in order. Break the pattern!"
  },
  {
    "clone_index": 8,
    "name": "RPS Copycat",
    "difficulty_modifier": 0.9,
    "ai_pattern": "mimic_player",
    "rounds_to_win": 5,
    "flavor_text": "AI copies your last throw. Don't repeat yourself!"
  },
  {
    "clone_index": 9,
    "name": "RPS Time Traveler",
    "difficulty_modifier": 1.2,
    "ai_pattern": "anti_player",
    "rounds_to_win": 5,
    "flavor_text": "AI throws what you threw 2 rounds ago. Memory test!"
  }
]
}
